Metadata-Version: 2.1
Name: ubit-autolab-commit-parser
Version: 0.0.4
Summary: Simple String Parsing for CICD Demo
Requires-Python: >=3.6, <4
